mirex/__init__.py
mirex/mirex.py
mirex/serializers/__init__.py
mirex/serializers/emoji.py
mirex/serializers/guild.py
mirex/serializers/role.py
mirex/serializers/sticker.py
mirex-0.1.0.dist-info/METADATA
mirex-0.1.0.dist-info/WHEEL
mirex-0.1.0.dist-info/top_level.txt
mirex-0.1.0.dist-info/RECORD
