Metadata-Version: 2.1
Name: mirex
Version: 0.1.0
Summary: Distributed Redis caching for discord bots.
Author: Skelmis
Author-email: ethanmkh2@gmail.com
Project-URL: Issue tracker, https://github.com/Skelmis/Mirex/issues
Project-URL: Documentation, https://mirex.rtfd.io/
Project-URL: Homepage, https://github.com/Skelmis/Mirex
Classifier: Programming Language :: Python :: 3
Classifier: License :: OSI Approved :: MIT License
Classifier: Operating System :: OS Independent
Requires-Python: >=3.10
Requires-Dist: redis (>=4.2)
Requires-Dist: orjson
Requires-Dist: hiredis
